Metadata-Version: 2.0
Name: nifty4gemini
Version: 1.0.1
Summary: Gemini Instruments Data Reduction Framework.
Home-page: http://www.gemini.edu
Author: mbusserolle
Author-email: mbussero@gemini.edu
License: MIT
Keywords: Gemini NIFS nifs pipeline reduction data IRAF iraf PYRAF pyraf astronomy integral field spectroscopy ifs ifu
Platform: UNKNOWN
Classifier: Development Status :: 5 - Production/Stable
Classifier: Environment :: MacOS X
Classifier: Intended Audience :: Science/Research
Classifier: Intended Audience :: Education
Classifier: License :: OSI Approved :: MIT License
Classifier: Operating System :: MacOS
Classifier: Programming Language :: Python :: 2.7
Classifier: Topic :: Scientific/Engineering :: Astronomy
Classifier: Topic :: Scientific/Engineering :: Physics
Requires-Python: ~=2.7
